pypago/__init__.py
pypago/areadiag.py
pypago/areas.py
pypago/coords.py
pypago/data.py
pypago/disp.py
pypago/grid.py
pypago/mat.py
pypago/misc.py
pypago/nc.py
pypago/plot.py
pypago/pyio.py
pypago/sample_param.py
pypago/secdiag.py
pypago/sections.py
pypago/toolsec.py
pypago/bin/__init__.py
pypago/bin/make_areas.py
pypago/bin/make_coords.py
pypago/bin/make_grid.py
pypago/bin/make_gridsec.py
pypago/guis/NewToolbar.py
pypago/guis/__init__.py
pypago/guis/_matplotlib_editions_sections.py
pypago/guis/_matplotlib_grid_model.py
pypago/guis/gui_grid_model.py
pypago/guis/gui_sections_edition.py
pypago-1.0.6.data/scripts/gui_grid_model.py
pypago-1.0.6.data/scripts/gui_sections_edition.py
pypago-1.0.6.data/scripts/make_areas.py
pypago-1.0.6.data/scripts/make_coords.py
pypago-1.0.6.data/scripts/make_grid.py
pypago-1.0.6.data/scripts/make_gridsec.py
pypago-1.0.6.dist-info/LICENSE
pypago-1.0.6.dist-info/METADATA
pypago-1.0.6.dist-info/WHEEL
pypago-1.0.6.dist-info/top_level.txt
pypago-1.0.6.dist-info/RECORD
