Metadata-Version: 2.1
Name: pypago
Version: 1.0.6
Summary: Python Physical Analysis of Gridded Ocean
Home-page: https://sourcesup.renater.fr/pago
Author: PAGO team
Author-email: pago-dev@groupes.renater.fr
Maintainer: Nicolas Barrier
Maintainer-email: nicolas.barrier@ird.fr
License: UNKNOWN
Keywords: ocean; grid model; transport; sections; budgets; heat; freshwater; ROMS; NEMO; IPSL; CNRM; GFDL
Platform: linux
Platform: mac osx
Classifier: Development Status :: 4 - Beta
Classifier: Intended Audience :: Science/Research
Classifier: Topic :: Scientific/Engineering :: Mathematics
Classifier: Topic :: Scientific/Engineering :: Physics
Classifier: Topic :: Scientific/Engineering :: Visualization
Classifier: Topic :: Scientific/Engineering :: Physics
Classifier: License :: OSI Approved :: GNU General Public License v3 or later (GPLv3+)
Classifier: Operating System :: MacOS :: MacOS X
Classifier: Operating System :: Unix
Classifier: Operating System :: POSIX :: Linux
Classifier: Programming Language :: Python :: 2.7
Classifier: Programming Language :: Python :: 3
Requires: numpy(>=1.9.2)
Requires: matplotlib(>=1.43)
Requires: basemap(>=1.0.7)
Requires: netcdf4(>1.1.9)
Requires-Dist: docutils (>=0.12)
Requires-Dist: sphinx (>=1.3.1)
Requires-Dist: pylint (>=1.4.2)
Requires-Dist: pyenchant (>=1.6.6)
Requires-Dist: pep8 (>=1.6.2)
Requires-Dist: pyflakes (>=0.9.2)
Requires-Dist: check-manifest (>=0.25)
Requires-Dist: numpy (>=1.9)
Requires-Dist: netCDF4 (>=1.1)
Requires-Dist: matplotlib (>=1.4)
Requires-Dist: basemap (>=1.0)
